fal_small_images/__init__.py
fal_small_images/__main__.py
fal_small_images/image_finder.py
fal_small_images/result.py
fal_small_images/row_result.py
fal_small_images/solr_client.py
fal_small_images-0.2.0.dist-info/METADATA
fal_small_images-0.2.0.dist-info/WHEEL
fal_small_images-0.2.0.dist-info/licenses/LICENSE
fal_small_images-0.2.0.dist-info/RECORD
