Metadata-Version: 2.4
Name: fal_small_images
Version: 0.2.0
Summary: Simple API to replace URNs pointing to low reslotion images with URNs pointing to hi-res images.
License:                                  Apache License
License-File: LICENSE
Requires-Python: >=3.13
Requires-Dist: python-dotenv>=1.0.1
